receptivefield/__init__.py
receptivefield/base.py
receptivefield/common.py
receptivefield/image.py
receptivefield/keras.py
receptivefield/logging.py
receptivefield/plotting.py
receptivefield/pytorch.py
receptivefield/types.py
receptivefield/resources/cat.jpg
receptivefield/resources/doge.jpg
receptivefield/resources/grumpy.jpg
receptivefield/resources/lena.jpg
receptivefield/resources/logger.conf
receptivefield-0.5.0.dist-info/LICENSE
receptivefield-0.5.0.dist-info/METADATA
receptivefield-0.5.0.dist-info/WHEEL
receptivefield-0.5.0.dist-info/top_level.txt
receptivefield-0.5.0.dist-info/RECORD
